graphlib/__init__.py
graphlib/graphlib.py
graphlib_backport-1.0.2.dist-info/WHEEL
graphlib_backport-1.0.2.dist-info/METADATA
graphlib_backport-1.0.2.dist-info/RECORD
