Metadata-Version: 2.1
Name: graphlib-backport
Version: 1.0.2
Summary: Backport of the Python 3.9 graphlib module for Python 3.6+
License: PSF
Author: Marius Helf
Author-email: helfsmarius@gmail.com
Requires-Python: >=3.6,<4.0
Classifier: License :: Other/Proprietary License
Classifier: Programming Language :: Python :: 3
Classifier: Programming Language :: Python :: 3.6
Classifier: Programming Language :: Python :: 3.7
Classifier: Programming Language :: Python :: 3.8
Classifier: Programming Language :: Python :: 3.9
